coloratem/__init__.py
coloratem-1.0.0.0.dist-info/METADATA
coloratem-1.0.0.0.dist-info/WHEEL
coloratem-1.0.0.0.dist-info/top_level.txt
coloratem-1.0.0.0.dist-info/RECORD
