Metadata-Version: 2.1
Name: coloratem
Version: 1.0.0.0
Summary: Cross-platform colored terminal text !
Author: benco
Author-email: benco@gmail.com
Classifier: Programming Language :: Python :: 3
Classifier: License :: OSI Approved :: MIT License
Classifier: Operating System :: OS Independent
